Metadata-Version: 2.1
Name: gnb-distributions-analyzer
Version: 0.1
Summary: Gaussian and Binomial distributions
Author: Amit Kumar Sharma
Author-email: ksamit1110@gmail.com
License: UNKNOWN
Platform: UNKNOWN
